pypagecache/__init__.py
pypagecache/cli.py
pypagecache/main.py
pypagecache/pagecache.py
pypagecache/syscallwrapperutils.py
pypagecache-0.5.0.dist-info/METADATA
pypagecache-0.5.0.dist-info/WHEEL
pypagecache-0.5.0.dist-info/entry_points.txt
pypagecache-0.5.0.dist-info/top_level.txt
pypagecache-0.5.0.dist-info/RECORD
