Metadata-Version: 2.1
Name: pypagecache
Version: 0.5.0
Summary: UNKNOWN
Home-page: UNKNOWN
License: UNKNOWN
Platform: UNKNOWN
